Traffic/FinalTransferSys.py
Traffic/FinalTransferSysTest.py
Traffic/NearStation.py
Traffic/ShuttleDict.py
Traffic/ShuttleTimeGo.py
Traffic/SpanTime.py
Traffic/SpanTimeNaver.py
Traffic/SubDIct.py
Traffic/SubTime.py
Traffic/SuttleDict.py
Traffic/__init__.py
Util/Eclass.py
Util/Gpss.py
Util/__init__.py
Weather/KorWeather.py
Weather/KorWeather_RainData.py
Weather/NaverWeather.py
Weather/OpenWeather.py
Weather/OpenWeatherImgFile.py
Weather/OpenWeather_ImgFile.py
Weather/VisualCrossing.py
Weather/WeatherTestData.py
Weather/WeatherZip.py
Weather/Weather_Test_Data.py
Weather/__init__.py
Tobi-0.0.2.1.dist-info/LICENSE
Tobi-0.0.2.1.dist-info/METADATA
Tobi-0.0.2.1.dist-info/WHEEL
Tobi-0.0.2.1.dist-info/top_level.txt
Tobi-0.0.2.1.dist-info/RECORD
